{
  "linkArray":
  [
    {
      "number": "1",
      "name": "The Domination Web",
      "status": "live",
      "url": "www.thedominationweb.com",
      "lastCheckedDate": "2014-11-20",
      "nextAction" : "Check status",
      "notes": "haven't checked for ages"
    },
    {
      "number": "2",
      "name": "The Mistress Web",
      "status": "live",
      "url": "www.themistressweb.com",
      "lastCheckedDate": "2014-11-20",
      "nextAction" : "Check status",
      "notes": "haven't checked for ages"
    },
    {
      "number": "3",
      "name": "Dommes",
      "status": "live",
      "url": "www.dommes.co.uk",
      "lastCheckedDate": "2014-11-20",
      "nextAction" : "Check status",
      "notes": "haven't checked for ages"
    }
  ]
}
